src/__init__.py
src/app.py
src/cli.py
src/constants.py
src/llm_client.py
src/utils.py
src/tools/__init__.py
src/tools/edit_file.py
src/tools/execute.py
src/tools/read_file.py
tass-0.1.12.dist-info/METADATA
tass-0.1.12.dist-info/WHEEL
tass-0.1.12.dist-info/entry_points.txt
tass-0.1.12.dist-info/licenses/LICENSE
tass-0.1.12.dist-info/RECORD
