Metadata-Version: 2.4
Name: tass
Version: 0.1.12
Summary: A terminal assistant that allows you to ask an LLM to run commands.
Project-URL: Homepage, https://github.com/cetincan0/tass
Author: Can Cetin
License: MIT
License-File: LICENSE
Requires-Python: >=3.10
Requires-Dist: prompt-toolkit>=3.0.52
Requires-Dist: requests>=2.32.5
Requires-Dist: rich>=14.2.0
